natch/__init__.py
natch/abstract/__init__.py
natch/abstract/hasher.py
natch/abstract/registry.py
natch/abstract/rule.py
natch/core/__init__.py
natch/core/decoration.py
natch/core/globals.py
natch/core/registry.py
natch/decorators/__init__.py
natch/decorators/all_of.py
natch/decorators/any.py
natch/decorators/any_of.py
natch/decorators/condition.py
natch/decorators/contains.py
natch/decorators/eq.py
natch/decorators/gt.py
natch/decorators/gte.py
natch/decorators/lt.py
natch/decorators/lte.py
natch/decorators/neq.py
natch/decorators/not_contains.py
natch/decorators/partial.py
natch/decorators/pattern.py
natch/exceptions/__init__.py
natch/exceptions/never_matches_error.py
natch/hashers/__init__.py
natch/hashers/qualname_hasher.py
natch/rules/__init__.py
natch/rules/all_of.py
natch/rules/any.py
natch/rules/any_of.py
natch/rules/condition.py
natch/rules/contains.py
natch/rules/eq.py
natch/rules/gt.py
natch/rules/gte.py
natch/rules/lt.py
natch/rules/lte.py
natch/rules/neq.py
natch/rules/not_contains.py
natch/rules/partial.py
natch/rules/pattern.py
natch-1.0.4.dist-info/LICENSE.txt
natch-1.0.4.dist-info/METADATA
natch-1.0.4.dist-info/WHEEL
natch-1.0.4.dist-info/top_level.txt
natch-1.0.4.dist-info/RECORD
